<?xml version="1.0" encoding="utf-8"?>

<resources>
  <style name="ToolbarTheme" parent="@android:style/Theme.Material.Light.DarkActionBar">
    <item name="android:windowNoTitle">true</item>
    <item name="android:windowActionBar">false</item>
    <item name="android:colorPrimary">#2196F3</item>
    <item name="android:colorPrimaryDark">#1976D2</item>
    <item name="android:colorAccent">#FF4081</item>
  </style>

  <style name="Theme.AppCompat.NoActionBar.FullScreen" parent="@android:style/Theme.Material">
    <item name="android:windowNoTitle">true</item>
    <item name="android:windowActionBar">false</item>
    <item name="android:windowFullscreen">true</item>
    <item name="android:windowContentOverlay">@null</item>
  </style>
</resources>